{
  "db_name": "PostgreSQL",
  "query": "\n        SELECT d.*\n        FROM documents AS d\n        LEFT JOIN users AS u ON d.user_uuid = u.uuid\n        WHERE d.uuid = $1 AND d.user_uuid = $2\n        ",
  "describe": {
    "columns": [
      {
        "ordinal": 0,
        "name": "uuid",
        "type_info": "Uuid"
      },
      {
        "ordinal": 1,
        "name": "user_uuid",
        "type_info": "Uuid"
      },
      {
        "ordinal": 2,
        "name": "title",
        "type_info": "Varchar"
      },
      {
        "ordinal": 3,
        "name": "content",
        "type_info": "Text"
      },
      {
        "ordinal": 4,
        "name": "created_at",
        "type_info": "Varchar"
      },
      {
        "ordinal": 5,
        "name": "updated_at",
        "type_info": "Varchar"
      }
    ],
    "parameters": {
      "Left": [
        "Uuid",
        "Uuid"
      ]
    },
    "nullable": [
      false,
      false,
      false,
      false,
      true,
      true
    ]
  },
  "hash": "40c97cdb0c1cb7aff0bd95fa6e0d012b40051d200ff86409d64a578777affd08"
}
